habitat_fydp_package/.DS_Store
habitat_fydp_package/Lake_Erie_Contours/Lake_Erie_Contours.dbf
habitat_fydp_package/Lake_Erie_Contours/Lake_Erie_Contours.prj
habitat_fydp_package/Lake_Erie_Contours/Lake_Erie_Contours.sbn
habitat_fydp_package/Lake_Erie_Contours/Lake_Erie_Contours.sbx
habitat_fydp_package/Lake_Erie_Contours/Lake_Erie_Contours.shp
habitat_fydp_package/Lake_Erie_Contours/Lake_Erie_Contours.shp.xml
habitat_fydp_package/Lake_Erie_Contours/Lake_Erie_Contours.shx
habitat_fydp_package/__init__.py
habitat_fydp_package/gsheet/.DS_Store
habitat_fydp_package/gsheet/client_secret.json
habitat_fydp_package/habitat_fydp_package.py
habitat_fydp_package/service_account.json
habitat_fydp_package-0.1.0.dist-info/WHEEL
habitat_fydp_package-0.1.0.dist-info/METADATA
habitat_fydp_package-0.1.0.dist-info/RECORD
