Metadata-Version: 2.1
Name: habitat-fydp-package
Version: 0.1.0
Summary: Democratize access to HAB related data in Lake Erie to be used for scientific research
Home-page: https://github.com/cognitetosh/habitat-fydp-package
License: MIT
Keywords: HAB,Harmful Algae Blooms,Lake Erie
Author: Shanthosh Pushparajah
Author-email: spushpar@uwaterloo.com
Requires-Python: >=3.7,<3.8
Classifier: License :: OSI Approved :: MIT License
Classifier: Programming Language :: Python :: 3
Classifier: Programming Language :: Python :: 3.7
Requires-Dist: DateTime (>=4.3,<5.0)
Requires-Dist: folium (>=0.12.1,<0.13.0)
Requires-Dist: google (>=3.0.0,<4.0.0)
Requires-Dist: google-auth-oauthlib (>=0.5.0,<0.6.0)
Requires-Dist: gspread (>=5.2.0,<6.0.0)
Requires-Dist: matplotlib (>=3.5.1,<4.0.0)
Requires-Dist: numpy (==1.19.3)
Requires-Dist: oauth2client (>=4.1.3,<5.0.0)
Requires-Dist: pandas (==1)
Requires-Dist: pmdarima (>=1.8.4,<2.0.0)
Requires-Dist: pyshp (>=2.1.3,<3.0.0)
Requires-Dist: requests (>=2.27.1,<3.0.0)
Requires-Dist: scikit-learn (>=1.0.2,<2.0.0)
Requires-Dist: scipy (>=1.7.3,<2.0.0)
Requires-Dist: sklearn (>=0.0,<0.1)
Requires-Dist: wwo-hist (>=0.0.7,<0.0.8)
Project-URL: Repository, https://github.com/cognitetosh/habitat-fydp-package
